biome/__init__.py
biome/text/__init__.py
biome/text/backbone.py
biome/text/commons.py
biome/text/configuration.py
biome/text/dataset.py
biome/text/errors.py
biome/text/features.py
biome/text/featurizer.py
biome/text/helpers.py
biome/text/hpo.py
biome/text/metrics.py
biome/text/mlflow_model.py
biome/text/model.py
biome/text/pipeline.py
biome/text/text_cleaning.py
biome/text/tokenizer.py
biome/text/trainer.py
biome/text/vocabulary.py
biome/text/cli/__init__.py
biome/text/cli/cli.py
biome/text/cli/evaluate.py
biome/text/cli/serve.py
biome/text/cli/train.py
biome/text/modules/__init__.py
biome/text/modules/configuration/__init__.py
biome/text/modules/configuration/allennlp_configuration.py
biome/text/modules/configuration/defs.py
biome/text/modules/encoders/__init__.py
biome/text/modules/encoders/time_distributed_encoder.py
biome/text/modules/heads/__init__.py
biome/text/modules/heads/language_modelling.py
biome/text/modules/heads/task_head.py
biome/text/modules/heads/task_prediction.py
biome/text/modules/heads/token_classification.py
biome/text/modules/heads/classification/__init__.py
biome/text/modules/heads/classification/classification.py
biome/text/modules/heads/classification/doc_classification.py
biome/text/modules/heads/classification/record_classification.py
biome/text/modules/heads/classification/record_pair_classification.py
biome/text/modules/heads/classification/relation_classification.py
biome/text/modules/heads/classification/text_classification.py
biome_text-3.3.0.dist-info/AUTHORS.rst
biome_text-3.3.0.dist-info/LICENSE.txt
biome_text-3.3.0.dist-info/METADATA
biome_text-3.3.0.dist-info/WHEEL
biome_text-3.3.0.dist-info/entry_points.txt
biome_text-3.3.0.dist-info/top_level.txt
biome_text-3.3.0.dist-info/RECORD
