Metadata-Version: 2.1
Name: biome-text
Version: 3.3.0
Summary: Biome-text is a light-weight open source Natural Language Processing toolbox built with AllenNLP
Home-page: https://www.recogn.ai/
Author: Recognai
Author-email: francisco@recogn.ai
License: UNKNOWN
Platform: UNKNOWN
Requires-Python: >=3.6.1
License-File: LICENSE.txt
License-File: AUTHORS.rst
Requires-Dist: allennlp (~=2.7.0)
Requires-Dist: beautifulsoup4 (~=4.9.0)
Requires-Dist: captum (~=0.2.0)
Requires-Dist: click (~=7.1.0)
Requires-Dist: datasets (<1.12.0,>=1.10.0)
Requires-Dist: flatdict (~=4.0.0)
Requires-Dist: lxml (~=4.6.2)
Requires-Dist: mlflow (<1.21.0,>=1.13.1)
Requires-Dist: numpy
Requires-Dist: pandas
Requires-Dist: pytorch-lightning (~=1.4.0)
Requires-Dist: ray[tune] (<1.7.0,>=1.3.0)
Requires-Dist: spacy (<3.2.0,>=2.3.0)
Requires-Dist: torch
Requires-Dist: transformers
Requires-Dist: tqdm (>=4.49.0)
Requires-Dist: fastapi (~=0.63.0)
Requires-Dist: uvicorn (>=0.13.0)
Requires-Dist: pyyaml
